mdw/__init__.cpython-36m-x86_64-linux-gnu.so
mdw/beamline/__init__.py
mdw/beamline/B5/B5.py
mdw/beamline/B5/__init__.py
mdw/beamline/B5/mdw_callback-10-24.py
mdw/beamline/B7/B7.py
mdw/beamline/B7/__init__.py
mdw/beamline/B7/generate_master.py
mdw/beamline/B7/mdw_b7.py
mdw/beamline/B7/mdw_bluesky_callback.py
mdw/beamline/B7/mdw_callback.py
mdw/beamline/B7/mdw_config.py
mdw/beamline/B7/mdw_config_detector.yaml
mdw/beamline/B7/mdw_config_mamba.yaml
mdw/beamline/B7/mdw_config_mdw.yaml
mdw/beamline/B8_tiaoguang/B8.py
mdw/beamline/B8_tiaoguang/__init__.py
mdw/beamline/B8_tiaoguang/mdw_b8_tiaoguang.py
mdw/beamline/B8_tiaoguang/mdw_bluesky_callback.py
mdw/beamline/B8_tiaoguang/mdw_callback.py
mdw/beamline/B8_tiaoguang/mdw_conf.yaml
mdw/beamline/B8_tiaoguang/mdw_config.py
mdw/beamline/BA/__init__.py
mdw/beamline/BA/mdw_ba.py
mdw/beamline/BA/mdw_config.py
mdw/beamline/BD/BD.py
mdw/beamline/BD/__init__.py
mdw/beamline/BD/mdw_bd.py
mdw/beamline/BD/mdw_bluesky_callback.py
mdw/beamline/BD/mdw_config.py
mdw/beamline/BE/BE.py
mdw/beamline/BE/__init__.py
mdw/beamline/BE/mdw_be.py
mdw/beamline/BE/mdw_bluesky_callback.py
mdw/beamline/BE/mdw_config.py
mdw/beamline/BE/test.py
mdw/callback/__init__.py
mdw/callback/start_collect_stop.py
mdw/callback/test.py
mdw/core/__init__.cpython-36m-x86_64-linux-gnu.so
mdw/core/dynamic_align_client.cpython-36m-x86_64-linux-gnu.so
mdw/core/log_zcl.cpython-36m-x86_64-linux-gnu.so
mdw/core/mdw_buffer.cpython-36m-x86_64-linux-gnu.so
mdw/core/mdw_conf.cpython-36m-x86_64-linux-gnu.so
mdw/core/mdw_dict.cpython-36m-x86_64-linux-gnu.so
mdw/core/mdw_dispatch.cpython-36m-x86_64-linux-gnu.so
mdw/core/mdw_function.cpython-36m-x86_64-linux-gnu.so
mdw/core/mdw_network.cpython-36m-x86_64-linux-gnu.so
mdw/node/__init__.cpython-36m-x86_64-linux-gnu.so
mdw/node/eiger.cpython-36m-x86_64-linux-gnu.so
mdw/node/jszx.cpython-36m-x86_64-linux-gnu.so
mdw/node/buffer/__init__.cpython-36m-x86_64-linux-gnu.so
mdw/node/buffer/bufferWorker.cpython-36m-x86_64-linux-gnu.so
mdw-1.1.1.4.2025.8.14.9.15.dist-info/METADATA
mdw-1.1.1.4.2025.8.14.9.15.dist-info/WHEEL
mdw-1.1.1.4.2025.8.14.9.15.dist-info/entry_points.txt
mdw-1.1.1.4.2025.8.14.9.15.dist-info/top_level.txt
mdw-1.1.1.4.2025.8.14.9.15.dist-info/RECORD
