Metadata-Version: 2.1
Name: mdw
Version: 1.1.1.4.2025.8.14.9.15
Summary: High Energy Photon Source Big Data Pipe Network
Home-page: UNKNOWN
Author: zhangchenglong
Author-email: zhangchl@ihep.ac.cn
License: Mozilla Public License 2.0
Platform: UNKNOWN
Requires-Python: >=3.0
Requires-Dist: numpy
Requires-Dist: Cython
Requires-Dist: setuptools-rust
Requires-Dist: wheel
Requires-Dist: h5py
Requires-Dist: setproctitle
Requires-Dist: multipledispatch
Requires-Dist: zmq
Requires-Dist: ruamel.yaml
Requires-Dist: lz4
Requires-Dist: bitshuffle
Requires-Dist: nb-log
Requires-Dist: kafka-python
Requires-Dist: redis
Requires-Dist: hdf5-zcl
Requires-Dist: fileservice
Requires-Dist: paramiko
